Metadata-Version: 2.1
Name: mofdb-client
Version: 0.10.0
Summary: Simple client for fetching data from mofdb
Home-page: https://github.com/n8ta/mofdb-client
Author: Nathaniel Tracy-Amoroso
Author-email: n8@u.northwestern.edu
Maintainer: Nathaniel Tracy-Amoroso
Maintainer-email: n8@u.northwestern.edu
License: MIT License
Project-URL: MofDB, https://mof.tech.northwestern.edu
Keywords: mofdb,client,metal organic frameworks,chemistry
Classifier: Programming Language :: Python :: 3
Classifier: License :: OSI Approved :: MIT License
Classifier: Operating System :: OS Independent
Requires-Python: >=3.7
License-File: LICENSE
Requires-Dist: requests (<3.0.0,>=2.20.1)
Requires-Dist: sentry-sdk (<2.0.0,>=1.5.8)
Requires-Dist: stream-unzip (<1.0.0,>=0.0.70)
